pyAprilTag/__init__.py
pyAprilTag/_apriltag.cp36-win_amd64.pyd
pyAprilTag/demo.py
pyAprilTag/demo_calib.py
pyAprilTag/demo_calib_by_photo.py
pyAprilTag/demo_plt.py
pyAprilTag/vdemo_cv.py
pyAprilTag/vdemo_plt.py
pyAprilTag/data/calib_pattern_Tag36h11.png
pyAprilTag/data/calib/AprilCalib_orgframe_00000.png
pyAprilTag/data/calib/AprilCalib_orgframe_00001.png
pyAprilTag/data/calib/AprilCalib_orgframe_00002.png
pyAprilTag/data/calib/AprilCalib_orgframe_00003.png
pyAprilTag/data/calib/AprilCalib_orgframe_00004.png
pyAprilTag/data/calib/AprilCalib_orgframe_00005.png
pyAprilTag/data/calib/AprilCalib_orgframe_00006.png
pyAprilTag/data/calib/AprilCalib_orgframe_00007.png
pyAprilTag/data/calib/AprilCalib_orgframe_00008.png
pyAprilTag/data/calib/AprilCalib_orgframe_00009.png
pyAprilTag-0.0.5.dist-info/METADATA
pyAprilTag-0.0.5.dist-info/RECORD
pyAprilTag-0.0.5.dist-info/WHEEL
pyAprilTag-0.0.5.dist-info/top_level.txt
