Metadata-Version: 2.1
Name: pyAprilTag
Version: 0.0.5
Summary: python wrapper for AprilTag implemented in library cv2cg
Home-page: https://github.com/ai4ce/pyAprilTag
Author: Chen Feng
Author-email: cfeng@nyu.edu
License: BSD
Platform: UNKNOWN
Requires-Dist: opencv (<4,>2)
